opencmiss/__init__.py
opencmiss/zincwidgets/__init__.py
opencmiss/zincwidgets/alignmentsceneviewerwidget.py
opencmiss/zincwidgets/fieldchooserwidget.py
opencmiss/zincwidgets/glyphchooserwidget.py
opencmiss/zincwidgets/graphicseditorwidget.py
opencmiss/zincwidgets/graphicseditorwidget_ui.py
opencmiss/zincwidgets/materialchooserwidget.py
opencmiss/zincwidgets/regionchooserwidget.py
opencmiss/zincwidgets/sceneeditorwidget.py
opencmiss/zincwidgets/sceneeditorwidget_ui.py
opencmiss/zincwidgets/sceneviewereditorwidget.py
opencmiss/zincwidgets/sceneviewereditorwidget_ui.py
opencmiss/zincwidgets/sceneviewerwidget.py
opencmiss.zincwidgets-2.0.0.dist-info/LICENSE
opencmiss.zincwidgets-2.0.0.dist-info/METADATA
opencmiss.zincwidgets-2.0.0.dist-info/WHEEL
opencmiss.zincwidgets-2.0.0.dist-info/top_level.txt
opencmiss.zincwidgets-2.0.0.dist-info/RECORD
