Metadata-Version: 2.1
Name: opencmiss.zincwidgets
Version: 2.0.0
Summary: UNKNOWN
Home-page: https://github.com/OpenCMISS-Bindings/opencmiss.zincwidgets/
Author: H. Sorby
Author-email: h.sorby@auckland.ac.nz
License: Mozilla Public License
Platform: any
Classifier: Development Status :: 5 - Production/Stable
Classifier: Intended Audience :: Developers
Classifier: Intended Audience :: Education
Classifier: Intended Audience :: Science/Research
Classifier: License :: OSI Approved :: Mozilla Public License 2.0 (MPL 2.0)
Classifier: Programming Language :: Python
Classifier: Operating System :: Microsoft :: Windows
Classifier: Operating System :: Unix
Classifier: Operating System :: MacOS :: MacOS X
Classifier: Topic :: Scientific/Engineering :: Medical Science Apps.
Classifier: Topic :: Scientific/Engineering :: Visualization
Classifier: Topic :: Software Development :: Libraries :: Python Modules
Requires-Dist: opencmiss.utils (>=0.2.0)
Requires-Dist: PySide2
Requires-Dist: opencmiss.zinc
